Workbook

Sheet Week-by-Week Plan
A1: Renovation Project Spend Tracker (Fill As You Go)
A2: Project Address: | B2: 46 Glenferrie Road, St Albans, AL1 4JU
A3: Assumptions: | B3: Fill in the details as you go: Task/Description, Category, Trade, supplier + receipt details, then enter hours/qty and unit costs. Totals update automatically. Edit labour rates in Lookups.
A5: Week # | B5: Task / Description | C5: Category | D5: Trade | E5: Location/Room | F5: Dependencies/Notes | G5: Supplier | H5: Invoice/Receipt Ref | I5: Paid Date | J5: Payment Method | K5: Hours (Labour) | L5: Rate (£/hr) | M5: Labour Cost (£) | N5: Qty (Materials) | O5: Unit Cost (£) | P5: Materials Cost (£) | Q5: VAT | R5: Total incl. VAT (£) | S5: Status
A6: Week 1
A7: 1 | B7: Labourers | C7: Labour | D7: General Builder | F7: Clearence - 6 man days | I7: Friday 27/2 | J7: Cash | L7: {=_xlfn.IFERROR(VLOOKUP(D7,'Lookups'!$A$2:$C$17,2,FALSE),0)} -> 45 | M7: 450 | P7: {=N7*O7} -> 0 | Q7: 0 | R7: {=(M7+P7)*(1+VALUE(SUBSTITUTE(Q7,"%",""))/100)} -> 450 | S7: Planned
A8: 1 | B8: DMC - Dave | C8: Labour | D8: General Builder | F8: Dave first day on site | I8: Friday 27/2 | J8: Cash | L8: {=_xlfn.IFERROR(VLOOKUP(D8,'Lookups'!$A$2:$C$17,2,FALSE),0)} -> 45 | M8: 220 | P8: {=N8*O8} -> 0 | Q8: 0 | R8: {=(M8+P8)*(1+VALUE(SUBSTITUTE(Q8,"%",""))/100)} -> 220 | S8: Planned
A9: 1 | B9: Adam - Clearance | C9: Labour | D9: Skip/Disposal | F9: Rubbish Removal | I9: Friday 27/2 | J9: Cash | L9: {=_xlfn.IFERROR(VLOOKUP(D9,'Lookups'!$A$2:$C$17,2,FALSE),0)} -> 0 | M9: 1100 | P9: {=N9*O9} -> 0 | Q9: 0 | R9: {=(M9+P9)*(1+VALUE(SUBSTITUTE(Q9,"%",""))/100)} -> 1100 | S9: Planned
A10: 1 | L10: {=_xlfn.IFERROR(VLOOKUP(D10,'Lookups'!$A$2:$C$17,2,FALSE),0)} -> 0 | M10: {=K10*L10} -> 0 | P10: {=N10*O10} -> 0 | Q10: 20% | R10: {=(M10+P10)*(1+VALUE(SUBSTITUTE(Q10,"%",""))/100)} -> 0 | S10: Planned
A11: 1 | L11: {=_xlfn.IFERROR(VLOOKUP(D11,'Lookups'!$A$2:$C$17,2,FALSE),0)} -> 0 | M11: {=K11*L11} -> 0 | P11: {=N11*O11} -> 0 | Q11: 20% | R11: {=(M11+P11)*(1+VALUE(SUBSTITUTE(Q11,"%",""))/100)} -> 0 | S11: Planned
A12: 1 | L12: {=_xlfn.IFERROR(VLOOKUP(D12,'Lookups'!$A$2:$C$17,2,FALSE),0)} -> 0 | M12: {=K12*L12} -> 0 | P12: {=N12*O12} -> 0 | Q12: 20% | R12: {=(M12+P12)*(1+VALUE(SUBSTITUTE(Q12,"%",""))/100)} -> 0 | S12: Planned
A13: 1 | L13: {=_xlfn.IFERROR(VLOOKUP(D13,'Lookups'!$A$2:$C$17,2,FALSE),0)} -> 0 | M13: {=K13*L13} -> 0 | P13: {=N13*O13} -> 0 | Q13: 20% | R13: {=(M13+P13)*(1+VALUE(SUBSTITUTE(Q13,"%",""))/100)} -> 0 | S13: Planned
A14: 1 | L14: {=_xlfn.IFERROR(VLOOKUP(D14,'Lookups'!$A$2:$C$17,2,FALSE),0)} -> 0 | M14: {=K14*L14} -> 0 | P14: {=N14*O14} -> 0 | Q14: 20% | R14: {=(M14+P14)*(1+VALUE(SUBSTITUTE(Q14,"%",""))/100)} -> 0 | S14: Planned
A15: 1 | L15: {=_xlfn.IFERROR(VLOOKUP(D15,'Lookups'!$A$2:$C$17,2,FALSE),0)} -> 0 | M15: {=K15*L15} -> 0 | P15: {=N15*O15} -> 0 | Q15: 20% | R15: {=(M15+P15)*(1+VALUE(SUBSTITUTE(Q15,"%",""))/100)} -> 0 | S15: Planned
A16: 1 | L16: {=_xlfn.IFERROR(VLOOKUP(D16,'Lookups'!$A$2:$C$17,2,FALSE),0)} -> 0 | M16: {=K16*L16} -> 0 | P16: {=N16*O16} -> 0 | Q16: 20% | R16: {=(M16+P16)*(1+VALUE(SUBSTITUTE(Q16,"%",""))/100)} -> 0 | S16: Planned
A17: 1 | L17: {=_xlfn.IFERROR(VLOOKUP(D17,'Lookups'!$A$2:$C$17,2,FALSE),0)} -> 0 | M17: {=K17*L17} -> 0 | P17: {=N17*O17} -> 0 | Q17: 20% | R17: {=(M17+P17)*(1+VALUE(SUBSTITUTE(Q17,"%",""))/100)} -> 0 | S17: Planned
A18: 1 | L18: {=_xlfn.IFERROR(VLOOKUP(D18,'Lookups'!$A$2:$C$17,2,FALSE),0)} -> 0 | M18: {=K18*L18} -> 0 | P18: {=N18*O18} -> 0 | Q18: 20% | R18: {=(M18+P18)*(1+VALUE(SUBSTITUTE(Q18,"%",""))/100)} -> 0 | S18: Planned
A19: Week 2
A20: 2 | B20: Labourers | C20: Labour | D20: General Builder | F20: Clearence / back to brick - 9 d | I20: Friday 6/3 | J20: Cash | L20: {=_xlfn.IFERROR(VLOOKUP(D20,'Lookups'!$A$2:$C$17,2,FALSE),0)} -> 45 | M20: 675 | P20: {=N20*O20} -> 0 | Q20: 0 | R20: {=(M20+P20)*(1+VALUE(SUBSTITUTE(Q20,"%",""))/100)} -> 675 | S20: Planned
A21: 2 | B21: Adam - Clearance | C21: Labour | D21: Skip/Disposal | F21: Rubbish Removal | I21: Friday 6/3 | J21: Cash | L21: {=_xlfn.IFERROR(VLOOKUP(D21,'Lookups'!$A$2:$C$17,2,FALSE),0)} -> 0 | M21: 1000 | P21: {=N21*O21} -> 0 | Q21: 0 | R21: {=(M21+P21)*(1+VALUE(SUBSTITUTE(Q21,"%",""))/100)} -> 1000 | S21: Planned
A22: 2 | L22: {=_xlfn.IFERROR(VLOOKUP(D22,'Lookups'!$A$2:$C$17,2,FALSE),0)} -> 0 | M22: {=K22*L22} -> 0 | P22: {=N22*O22} -> 0 | Q22: 20% | R22: {=(M22+P22)*(1+VALUE(SUBSTITUTE(Q22,"%",""))/100)} -> 0 | S22: Planned
A23: 2 | L23: {=_xlfn.IFERROR(VLOOKUP(D23,'Lookups'!$A$2:$C$17,2,FALSE),0)} -> 0 | M23: {=K23*L23} -> 0 | P23: {=N23*O23} -> 0 | Q23: 20% | R23: {=(M23+P23)*(1+VALUE(SUBSTITUTE(Q23,"%",""))/100)} -> 0 | S23: Planned
A24: 2 | L24: {=_xlfn.IFERROR(VLOOKUP(D24,'Lookups'!$A$2:$C$17,2,FALSE),0)} -> 0 | M24: {=K24*L24} -> 0 | P24: {=N24*O24} -> 0 | Q24: 20% | R24: {=(M24+P24)*(1+VALUE(SUBSTITUTE(Q24,"%",""))/100)} -> 0 | S24: Planned
A25: 2 | L25: {=_xlfn.IFERROR(VLOOKUP(D25,'Lookups'!$A$2:$C$17,2,FALSE),0)} -> 0 | M25: {=K25*L25} -> 0 | P25: {=N25*O25} -> 0 | Q25: 20% | R25: {=(M25+P25)*(1+VALUE(SUBSTITUTE(Q25,"%",""))/100)} -> 0 | S25: Planned
A26: 2 | L26: {=_xlfn.IFERROR(VLOOKUP(D26,'Lookups'!$A$2:$C$17,2,FALSE),0)} -> 0 | M26: {=K26*L26} -> 0 | P26: {=N26*O26} -> 0 | Q26: 20% | R26: {=(M26+P26)*(1+VALUE(SUBSTITUTE(Q26,"%",""))/100)} -> 0 | S26: Planned
A27: 2 | L27: {=_xlfn.IFERROR(VLOOKUP(D27,'Lookups'!$A$2:$C$17,2,FALSE),0)} -> 0 | M27: {=K27*L27} -> 0 | P27: {=N27*O27} -> 0 | Q27: 20% | R27: {=(M27+P27)*(1+VALUE(SUBSTITUTE(Q27,"%",""))/100)} -> 0 | S27: Planned
A28: 2 | L28: {=_xlfn.IFERROR(VLOOKUP(D28,'Lookups'!$A$2:$C$17,2,FALSE),0)} -> 0 | M28: {=K28*L28} -> 0 | P28: {=N28*O28} -> 0 | Q28: 20% | R28: {=(M28+P28)*(1+VALUE(SUBSTITUTE(Q28,"%",""))/100)} -> 0 | S28: Planned
A29: 2 | L29: {=_xlfn.IFERROR(VLOOKUP(D29,'Lookups'!$A$2:$C$17,2,FALSE),0)} -> 0 | M29: {=K29*L29} -> 0 | P29: {=N29*O29} -> 0 | Q29: 20% | R29: {=(M29+P29)*(1+VALUE(SUBSTITUTE(Q29,"%",""))/100)} -> 0 | S29: Planned
A30: 2 | L30: {=_xlfn.IFERROR(VLOOKUP(D30,'Lookups'!$A$2:$C$17,2,FALSE),0)} -> 0 | M30: {=K30*L30} -> 0 | P30: {=N30*O30} -> 0 | Q30: 20% | R30: {=(M30+P30)*(1+VALUE(SUBSTITUTE(Q30,"%",""))/100)} -> 0 | S30: Planned
A31: 2 | L31: {=_xlfn.IFERROR(VLOOKUP(D31,'Lookups'!$A$2:$C$17,2,FALSE),0)} -> 0 | M31: {=K31*L31} -> 0 | P31: {=N31*O31} -> 0 | Q31: 20% | R31: {=(M31+P31)*(1+VALUE(SUBSTITUTE(Q31,"%",""))/100)} -> 0 | S31: Planned
A32: Week 3
A33: 3 | B33: Labourers | C33: Labour | D33: General Builder | F33: Clearence / back to brick - 7 d | I33: Friday 13/3 | J33: Cash | L33: {=_xlfn.IFERROR(VLOOKUP(D33,'Lookups'!$A$2:$C$17,2,FALSE),0)} -> 45 | M33: 525 | P33: {=N33*O33} -> 0 | Q33: 0 | R33: {=(M33+P33)*(1+VALUE(SUBSTITUTE(Q33,"%",""))/100)} -> 525 | S33: Planned
A34: 3 | L34: {=_xlfn.IFERROR(VLOOKUP(D34,'Lookups'!$A$2:$C$17,2,FALSE),0)} -> 0 | M34: {=K34*L34} -> 0 | P34: {=N34*O34} -> 0 | Q34: 20% | R34: {=(M34+P34)*(1+VALUE(SUBSTITUTE(Q34,"%",""))/100)} -> 0 | S34: Planned
A35: 3 | L35: {=_xlfn.IFERROR(VLOOKUP(D35,'Lookups'!$A$2:$C$17,2,FALSE),0)} -> 0 | M35: {=K35*L35} -> 0 | P35: {=N35*O35} -> 0 | Q35: 20% | R35: {=(M35+P35)*(1+VALUE(SUBSTITUTE(Q35,"%",""))/100)} -> 0 | S35: Planned
A36: 3 | L36: {=_xlfn.IFERROR(VLOOKUP(D36,'Lookups'!$A$2:$C$17,2,FALSE),0)} -> 0 | M36: {=K36*L36} -> 0 | P36: {=N36*O36} -> 0 | Q36: 20% | R36: {=(M36+P36)*(1+VALUE(SUBSTITUTE(Q36,"%",""))/100)} -> 0 | S36: Planned
A37: 3 | L37: {=_xlfn.IFERROR(VLOOKUP(D37,'Lookups'!$A$2:$C$17,2,FALSE),0)} -> 0 | M37: {=K37*L37} -> 0 | P37: {=N37*O37} -> 0 | Q37: 20% | R37: {=(M37+P37)*(1+VALUE(SUBSTITUTE(Q37,"%",""))/100)} -> 0 | S37: Planned
A38: 3 | L38: {=_xlfn.IFERROR(VLOOKUP(D38,'Lookups'!$A$2:$C$17,2,FALSE),0)} -> 0 | M38: {=K38*L38} -> 0 | P38: {=N38*O38} -> 0 | Q38: 0% | R38: {=(M38+P38)*(1+VALUE(SUBSTITUTE(Q38,"%",""))/100)} -> 0 | S38: Planned
A39: 3 | L39: {=_xlfn.IFERROR(VLOOKUP(D39,'Lookups'!$A$2:$C$17,2,FALSE),0)} -> 0 | M39: {=K39*L39} -> 0 | P39: {=N39*O39} -> 0 | Q39: 20% | R39: {=(M39+P39)*(1+VALUE(SUBSTITUTE(Q39,"%",""))/100)} -> 0 | S39: Planned
A40: 3 | L40: {=_xlfn.IFERROR(VLOOKUP(D40,'Lookups'!$A$2:$C$17,2,FALSE),0)} -> 0 | M40: {=K40*L40} -> 0 | P40: {=N40*O40} -> 0 | Q40: 20% | R40: {=(M40+P40)*(1+VALUE(SUBSTITUTE(Q40,"%",""))/100)} -> 0 | S40: Planned
A41: 3 | L41: {=_xlfn.IFERROR(VLOOKUP(D41,'Lookups'!$A$2:$C$17,2,FALSE),0)} -> 0 | M41: {=K41*L41} -> 0 | P41: {=N41*O41} -> 0 | Q41: 20% | R41: {=(M41+P41)*(1+VALUE(SUBSTITUTE(Q41,"%",""))/100)} -> 0 | S41: Planned
A42: 3 | L42: {=_xlfn.IFERROR(VLOOKUP(D42,'Lookups'!$A$2:$C$17,2,FALSE),0)} -> 0 | M42: {=K42*L42} -> 0 | P42: {=N42*O42} -> 0 | Q42: 20% | R42: {=(M42+P42)*(1+VALUE(SUBSTITUTE(Q42,"%",""))/100)} -> 0 | S42: Planned
A43: 3 | L43: {=_xlfn.IFERROR(VLOOKUP(D43,'Lookups'!$A$2:$C$17,2,FALSE),0)} -> 0 | M43: {=K43*L43} -> 0 | P43: {=N43*O43} -> 0 | Q43: 20% | R43: {=(M43+P43)*(1+VALUE(SUBSTITUTE(Q43,"%",""))/100)} -> 0 | S43: Planned
A44: 3 | L44: {=_xlfn.IFERROR(VLOOKUP(D44,'Lookups'!$A$2:$C$17,2,FALSE),0)} -> 0 | M44: {=K44*L44} -> 0 | P44: {=N44*O44} -> 0 | Q44: 20% | R44: {=(M44+P44)*(1+VALUE(SUBSTITUTE(Q44,"%",""))/100)} -> 0 | S44: Planned
A45: Week 4
A46: 4 | B46: Labourers | C46: Labour | D46: General Builder | F46: Clearance 6d | I46: Friday 20/3 | J46: Cash | L46: {=_xlfn.IFERROR(VLOOKUP(D46,'Lookups'!$A$2:$C$17,2,FALSE),0)} -> 45 | M46: 450 | P46: {=N46*O46} -> 0 | Q46: 0 | R46: {=(M46+P46)*(1+VALUE(SUBSTITUTE(Q46,"%",""))/100)} -> 450 | S46: Planned
A47: 4 | B47: Adam - Clearance | C47: Labour | D47: Skip/Disposal | I47: Friday 20/3 | J47: Cash | L47: {=_xlfn.IFERROR(VLOOKUP(D47,'Lookups'!$A$2:$C$17,2,FALSE),0)} -> 0 | M47: 1100 | P47: {=N47*O47} -> 0 | Q47: 0 | R47: {=(M47+P47)*(1+VALUE(SUBSTITUTE(Q47,"%",""))/100)} -> 1100 | S47: Planned
A48: 4 | L48: {=_xlfn.IFERROR(VLOOKUP(D48,'Lookups'!$A$2:$C$17,2,FALSE),0)} -> 0 | M48: {=K48*L48} -> 0 | P48: {=N48*O48} -> 0 | Q48: 20% | R48: {=(M48+P48)*(1+VALUE(SUBSTITUTE(Q48,"%",""))/100)} -> 0 | S48: Planned
A49: 4 | L49: {=_xlfn.IFERROR(VLOOKUP(D49,'Lookups'!$A$2:$C$17,2,FALSE),0)} -> 0 | M49: {=K49*L49} -> 0 | P49: {=N49*O49} -> 0 | Q49: 20% | R49: {=(M49+P49)*(1+VALUE(SUBSTITUTE(Q49,"%",""))/100)} -> 0 | S49: Planned
A50: 4 | L50: {=_xlfn.IFERROR(VLOOKUP(D50,'Lookups'!$A$2:$C$17,2,FALSE),0)} -> 0 | M50: {=K50*L50} -> 0 | P50: {=N50*O50} -> 0 | Q50: 20% | R50: {=(M50+P50)*(1+VALUE(SUBSTITUTE(Q50,"%",""))/100)} -> 0 | S50: Planned
A51: 4 | L51: {=_xlfn.IFERROR(VLOOKUP(D51,'Lookups'!$A$2:$C$17,2,FALSE),0)} -> 0 | M51: {=K51*L51} -> 0 | P51: {=N51*O51} -> 0 | Q51: 20% | R51: {=(M51+P51)*(1+VALUE(SUBSTITUTE(Q51,"%",""))/100)} -> 0 | S51: Planned
A52: 4 | L52: {=_xlfn.IFERROR(VLOOKUP(D52,'Lookups'!$A$2:$C$17,2,FALSE),0)} -> 0 | M52: {=K52*L52} -> 0 | P52: {=N52*O52} -> 0 | Q52: 20% | R52: {=(M52+P52)*(1+VALUE(SUBSTITUTE(Q52,"%",""))/100)} -> 0 | S52: Planned
A53: 4 | L53: {=_xlfn.IFERROR(VLOOKUP(D53,'Lookups'!$A$2:$C$17,2,FALSE),0)} -> 0 | M53: {=K53*L53} -> 0 | P53: {=N53*O53} -> 0 | Q53: 20% | R53: {=(M53+P53)*(1+VALUE(SUBSTITUTE(Q53,"%",""))/100)} -> 0 | S53: Planned
A54: 4 | L54: {=_xlfn.IFERROR(VLOOKUP(D54,'Lookups'!$A$2:$C$17,2,FALSE),0)} -> 0 | M54: {=K54*L54} -> 0 | P54: {=N54*O54} -> 0 | Q54: 20% | R54: {=(M54+P54)*(1+VALUE(SUBSTITUTE(Q54,"%",""))/100)} -> 0 | S54: Planned
A55: 4 | L55: {=_xlfn.IFERROR(VLOOKUP(D55,'Lookups'!$A$2:$C$17,2,FALSE),0)} -> 0 | M55: {=K55*L55} -> 0 | P55: {=N55*O55} -> 0 | Q55: 20% | R55: {=(M55+P55)*(1+VALUE(SUBSTITUTE(Q55,"%",""))/100)} -> 0 | S55: Planned
A56: 4 | L56: {=_xlfn.IFERROR(VLOOKUP(D56,'Lookups'!$A$2:$C$17,2,FALSE),0)} -> 0 | M56: {=K56*L56} -> 0 | P56: {=N56*O56} -> 0 | Q56: 20% | R56: {=(M56+P56)*(1+VALUE(SUBSTITUTE(Q56,"%",""))/100)} -> 0 | S56: Planned
A57: 4 | L57: {=_xlfn.IFERROR(VLOOKUP(D57,'Lookups'!$A$2:$C$17,2,FALSE),0)} -> 0 | M57: {=K57*L57} -> 0 | P57: {=N57*O57} -> 0 | Q57: 20% | R57: {=(M57+P57)*(1+VALUE(SUBSTITUTE(Q57,"%",""))/100)} -> 0 | S57: Planned
A58: Week 5
A59: 5 | B59: Skip | C59: Labour | D59: Skip/Disposal | G59: Stevenage Skips | I59: Friday 27/3 | J59: Cash | L59: {=_xlfn.IFERROR(VLOOKUP(D59,'Lookups'!$A$2:$C$17,2,FALSE),0)} -> 0 | M59: 480 | P59: {=N59*O59} -> 0 | Q59: 0 | R59: {=(M59+P59)*(1+VALUE(SUBSTITUTE(Q59,"%",""))/100)} -> 480 | S59: Planned
A60: 5 | B60: Labourers | C60: Labour | D60: General Builder | I60: Friday 27/3 | J60: Cash | L60: {=_xlfn.IFERROR(VLOOKUP(D60,'Lookups'!$A$2:$C$17,2,FALSE),0)} -> 45 | M60: 450 | P60: {=N60*O60} -> 0 | Q60: 0 | R60: {=(M60+P60)*(1+VALUE(SUBSTITUTE(Q60,"%",""))/100)} -> 450 | S60: Planned
A61: 5 | B61: Dave Barker (Groundwork) | C61: Labour | D61: General Builder | I61: Friday 27/3 | J61: Cash | L61: {=_xlfn.IFERROR(VLOOKUP(D61,'Lookups'!$A$2:$C$17,2,FALSE),0)} -> 45 | M61: 1250 | P61: {=N61*O61} -> 0 | Q61: 0 | R61: {=(M61+P61)*(1+VALUE(SUBSTITUTE(Q61,"%",""))/100)} -> 1250 | S61: Planned
A62: 5 | B62: Master Mix | C62: Materials | D62: Other | I62: Friday 27/3 | J62: Debit Card | L62: {=_xlfn.IFERROR(VLOOKUP(D62,'Lookups'!$A$2:$C$17,2,FALSE),0)} -> 50 | M62: 1025 | P62: {=N62*O62} -> 0 | Q62: 0 | R62: {=(M62+P62)*(1+VALUE(SUBSTITUTE(Q62,"%",""))/100)} -> 1025 | S62: Planned
A63: 5 | L63: {=_xlfn.IFERROR(VLOOKUP(D63,'Lookups'!$A$2:$C$17,2,FALSE),0)} -> 0 | M63: {=K63*L63} -> 0 | P63: {=N63*O63} -> 0 | Q63: 20% | R63: {=(M63+P63)*(1+VALUE(SUBSTITUTE(Q63,"%",""))/100)} -> 0 | S63: Planned
A64: 5 | L64: {=_xlfn.IFERROR(VLOOKUP(D64,'Lookups'!$A$2:$C$17,2,FALSE),0)} -> 0 | M64: {=K64*L64} -> 0 | P64: {=N64*O64} -> 0 | Q64: 20% | R64: {=(M64+P64)*(1+VALUE(SUBSTITUTE(Q64,"%",""))/100)} -> 0 | S64: Planned
A65: 5 | L65: {=_xlfn.IFERROR(VLOOKUP(D65,'Lookups'!$A$2:$C$17,2,FALSE),0)} -> 0 | M65: {=K65*L65} -> 0 | P65: {=N65*O65} -> 0 | Q65: 20% | R65: {=(M65+P65)*(1+VALUE(SUBSTITUTE(Q65,"%",""))/100)} -> 0 | S65: Planned
A66: 5 | L66: {=_xlfn.IFERROR(VLOOKUP(D66,'Lookups'!$A$2:$C$17,2,FALSE),0)} -> 0 | M66: {=K66*L66} -> 0 | P66: {=N66*O66} -> 0 | Q66: 20% | R66: {=(M66+P66)*(1+VALUE(SUBSTITUTE(Q66,"%",""))/100)} -> 0 | S66: Planned
A67: 5 | L67: {=_xlfn.IFERROR(VLOOKUP(D67,'Lookups'!$A$2:$C$17,2,FALSE),0)} -> 0 | M67: {=K67*L67} -> 0 | P67: {=N67*O67} -> 0 | Q67: 20% | R67: {=(M67+P67)*(1+VALUE(SUBSTITUTE(Q67,"%",""))/100)} -> 0 | S67: Planned
A68: 5 | L68: {=_xlfn.IFERROR(VLOOKUP(D68,'Lookups'!$A$2:$C$17,2,FALSE),0)} -> 0 | M68: {=K68*L68} -> 0 | P68: {=N68*O68} -> 0 | Q68: 20% | R68: {=(M68+P68)*(1+VALUE(SUBSTITUTE(Q68,"%",""))/100)} -> 0 | S68: Planned
A69: 5 | L69: {=_xlfn.IFERROR(VLOOKUP(D69,'Lookups'!$A$2:$C$17,2,FALSE),0)} -> 0 | M69: {=K69*L69} -> 0 | P69: {=N69*O69} -> 0 | Q69: 20% | R69: {=(M69+P69)*(1+VALUE(SUBSTITUTE(Q69,"%",""))/100)} -> 0 | S69: Planned
A70: 5 | L70: {=_xlfn.IFERROR(VLOOKUP(D70,'Lookups'!$A$2:$C$17,2,FALSE),0)} -> 0 | M70: {=K70*L70} -> 0 | P70: {=N70*O70} -> 0 | Q70: 0% | R70: {=(M70+P70)*(1+VALUE(SUBSTITUTE(Q70,"%",""))/100)} -> 0 | S70: Planned
A71: Week 6
A72: 6 | B72: Labourers | C72: Labour | D72: General Builder | I72: Friday 3/4 | J72: Cash | L72: {=_xlfn.IFERROR(VLOOKUP(D72,'Lookups'!$A$2:$C$17,2,FALSE),0)} -> 45 | M72: 300 | P72: {=N72*O72} -> 0 | Q72: 0 | R72: {=(M72+P72)*(1+VALUE(SUBSTITUTE(Q72,"%",""))/100)} -> 300 | S72: Planned
A73: 6 | B73: Dave Barker (Groundwork) | C73: Labour | D73: General Builder | I73: Friday 3/4 | J73: Cash | L73: {=_xlfn.IFERROR(VLOOKUP(D73,'Lookups'!$A$2:$C$17,2,FALSE),0)} -> 45 | M73: 900 | P73: {=N73*O73} -> 0 | Q73: 0 | R73: {=(M73+P73)*(1+VALUE(SUBSTITUTE(Q73,"%",""))/100)} -> 900 | S73: Planned
A74: 6 | B74: Dave Builder | C74: Labour | D74: General Builder | I74: Friday 3/4 | J74: Cash | L74: {=_xlfn.IFERROR(VLOOKUP(D74,'Lookups'!$A$2:$C$17,2,FALSE),0)} -> 45 | M74: 300 | P74: {=N74*O74} -> 0 | Q74: 0 | R74: {=(M74+P74)*(1+VALUE(SUBSTITUTE(Q74,"%",""))/100)} -> 300 | S74: Planned
A75: 6 | B75: Steels | C75: Materials | D75: General Builder | I75: Friday 3/4 | J75: Cash | L75: {=_xlfn.IFERROR(VLOOKUP(D75,'Lookups'!$A$2:$C$17,2,FALSE),0)} -> 45 | M75: 1000 | P75: {=N75*O75} -> 0 | Q75: 0 | R75: {=(M75+P75)*(1+VALUE(SUBSTITUTE(Q75,"%",""))/100)} -> 1000 | S75: Planned
A76: 6 | L76: {=_xlfn.IFERROR(VLOOKUP(D76,'Lookups'!$A$2:$C$17,2,FALSE),0)} -> 0 | M76: {=K76*L76} -> 0 | P76: {=N76*O76} -> 0 | Q76: 20% | R76: {=(M76+P76)*(1+VALUE(SUBSTITUTE(Q76,"%",""))/100)} -> 0 | S76: Planned
A77: 6 | L77: {=_xlfn.IFERROR(VLOOKUP(D77,'Lookups'!$A$2:$C$17,2,FALSE),0)} -> 0 | M77: {=K77*L77} -> 0 | P77: {=N77*O77} -> 0 | Q77: 20% | R77: {=(M77+P77)*(1+VALUE(SUBSTITUTE(Q77,"%",""))/100)} -> 0 | S77: Planned
A78: 6 | L78: {=_xlfn.IFERROR(VLOOKUP(D78,'Lookups'!$A$2:$C$17,2,FALSE),0)} -> 0 | M78: {=K78*L78} -> 0 | P78: {=N78*O78} -> 0 | Q78: 20% | R78: {=(M78+P78)*(1+VALUE(SUBSTITUTE(Q78,"%",""))/100)} -> 0 | S78: Planned
A79: 6 | L79: {=_xlfn.IFERROR(VLOOKUP(D79,'Lookups'!$A$2:$C$17,2,FALSE),0)} -> 0 | M79: {=K79*L79} -> 0 | P79: {=N79*O79} -> 0 | Q79: 20% | R79: {=(M79+P79)*(1+VALUE(SUBSTITUTE(Q79,"%",""))/100)} -> 0 | S79: Planned
A80: 6 | L80: {=_xlfn.IFERROR(VLOOKUP(D80,'Lookups'!$A$2:$C$17,2,FALSE),0)} -> 0 | M80: {=K80*L80} -> 0 | P80: {=N80*O80} -> 0 | Q80: 20% | R80: {=(M80+P80)*(1+VALUE(SUBSTITUTE(Q80,"%",""))/100)} -> 0 | S80: Planned
A81: 6 | L81: {=_xlfn.IFERROR(VLOOKUP(D81,'Lookups'!$A$2:$C$17,2,FALSE),0)} -> 0 | M81: {=K81*L81} -> 0 | P81: {=N81*O81} -> 0 | Q81: 20% | R81: {=(M81+P81)*(1+VALUE(SUBSTITUTE(Q81,"%",""))/100)} -> 0 | S81: Planned
A82: 6 | L82: {=_xlfn.IFERROR(VLOOKUP(D82,'Lookups'!$A$2:$C$17,2,FALSE),0)} -> 0 | M82: {=K82*L82} -> 0 | P82: {=N82*O82} -> 0 | Q82: 20% | R82: {=(M82+P82)*(1+VALUE(SUBSTITUTE(Q82,"%",""))/100)} -> 0 | S82: Planned
A83: 6 | L83: {=_xlfn.IFERROR(VLOOKUP(D83,'Lookups'!$A$2:$C$17,2,FALSE),0)} -> 0 | M83: {=K83*L83} -> 0 | P83: {=N83*O83} -> 0 | Q83: 20% | R83: {=(M83+P83)*(1+VALUE(SUBSTITUTE(Q83,"%",""))/100)} -> 0 | S83: Planned
A84: Week 7
A85: 7 | B85: SDE Drainage | C85: Materials | D85: General Builder | I85: Friday 10/4 | J85: Credit Card | L85: {=_xlfn.IFERROR(VLOOKUP(D85,'Lookups'!$A$2:$C$17,2,FALSE),0)} -> 45 | M85: {=K85*L85} -> 0 | P85: {=N85*O85} -> 0 | Q85: 20% | R85: 98.4 | S85: Planned
A86: 7 | B86: Master Mix | C86: Materials | D86: General Builder | I86: Friday 10/4 | J86: Debit Card | L86: {=_xlfn.IFERROR(VLOOKUP(D86,'Lookups'!$A$2:$C$17,2,FALSE),0)} -> 45 | M86: {=K86*L86} -> 0 | P86: {=N86*O86} -> 0 | Q86: 20% | R86: 900 | S86: Planned
A87: 7 | B87: Labourers | C87: Labour | D87: General Builder | I87: FRIDAY 10/4 | J87: Cash | L87: {=_xlfn.IFERROR(VLOOKUP(D87,'Lookups'!$A$2:$C$17,2,FALSE),0)} -> 45 | M87: 450 | P87: {=N87*O87} -> 0 | Q87: 0 | R87: {=(M87+P87)*(1+VALUE(SUBSTITUTE(Q87,"%",""))/100)} -> 450 | S87: Planned
A88: 7 | B88: Dave | C88: Labour | D88: General Builder | G88: £300 PAID FROM OWED | I88: Friday 10/4 | J88: Cash | L88: {=_xlfn.IFERROR(VLOOKUP(D88,'Lookups'!$A$2:$C$17,2,FALSE),0)} -> 45 | M88: 600 | P88: {=N88*O88} -> 0 | Q88: 0 | R88: {=(M88+P88)*(1+VALUE(SUBSTITUTE(Q88,"%",""))/100)} -> 600 | S88: Planned
A89: 7 | L89: {=_xlfn.IFERROR(VLOOKUP(D89,'Lookups'!$A$2:$C$17,2,FALSE),0)} -> 0 | M89: {=K89*L89} -> 0 | P89: {=N89*O89} -> 0 | Q89: 20% | R89: {=(M89+P89)*(1+VALUE(SUBSTITUTE(Q89,"%",""))/100)} -> 0 | S89: Planned
A90: 7 | L90: {=_xlfn.IFERROR(VLOOKUP(D90,'Lookups'!$A$2:$C$17,2,FALSE),0)} -> 0 | M90: {=K90*L90} -> 0 | P90: {=N90*O90} -> 0 | Q90: 20% | R90: {=(M90+P90)*(1+VALUE(SUBSTITUTE(Q90,"%",""))/100)} -> 0 | S90: Planned
A91: 7 | L91: {=_xlfn.IFERROR(VLOOKUP(D91,'Lookups'!$A$2:$C$17,2,FALSE),0)} -> 0 | M91: {=K91*L91} -> 0 | P91: {=N91*O91} -> 0 | Q91: 20% | R91: {=(M91+P91)*(1+VALUE(SUBSTITUTE(Q91,"%",""))/100)} -> 0 | S91: Planned
A92: 7 | L92: {=_xlfn.IFERROR(VLOOKUP(D92,'Lookups'!$A$2:$C$17,2,FALSE),0)} -> 0 | M92: {=K92*L92} -> 0 | P92: {=N92*O92} -> 0 | Q92: 20% | R92: {=(M92+P92)*(1+VALUE(SUBSTITUTE(Q92,"%",""))/100)} -> 0 | S92: Planned
A93: 7 | L93: {=_xlfn.IFERROR(VLOOKUP(D93,'Lookups'!$A$2:$C$17,2,FALSE),0)} -> 0 | M93: {=K93*L93} -> 0 | P93: {=N93*O93} -> 0 | Q93: 20% | R93: {=(M93+P93)*(1+VALUE(SUBSTITUTE(Q93,"%",""))/100)} -> 0 | S93: Planned
A94: 7 | L94: {=_xlfn.IFERROR(VLOOKUP(D94,'Lookups'!$A$2:$C$17,2,FALSE),0)} -> 0 | M94: {=K94*L94} -> 0 | P94: {=N94*O94} -> 0 | Q94: 20% | R94: {=(M94+P94)*(1+VALUE(SUBSTITUTE(Q94,"%",""))/100)} -> 0 | S94: Planned
A95: 7 | L95: {=_xlfn.IFERROR(VLOOKUP(D95,'Lookups'!$A$2:$C$17,2,FALSE),0)} -> 0 | M95: {=K95*L95} -> 0 | P95: {=N95*O95} -> 0 | Q95: 20% | R95: {=(M95+P95)*(1+VALUE(SUBSTITUTE(Q95,"%",""))/100)} -> 0 | S95: Planned
A96: 7 | L96: {=_xlfn.IFERROR(VLOOKUP(D96,'Lookups'!$A$2:$C$17,2,FALSE),0)} -> 0 | M96: {=K96*L96} -> 0 | P96: {=N96*O96} -> 0 | Q96: 20% | R96: {=(M96+P96)*(1+VALUE(SUBSTITUTE(Q96,"%",""))/100)} -> 0 | S96: Planned
A97: Week 8
A98: 8 | B98: dave | C98: Labour | D98: General Builder | G98: £400 paid from whats owed | L98: {=_xlfn.IFERROR(VLOOKUP(D98,'Lookups'!$A$2:$C$17,2,FALSE),0)} -> 45 | M98: 1400 | P98: {=N98*O98} -> 0 | Q98: 0 | R98: {=(M98+P98)*(1+VALUE(SUBSTITUTE(Q98,"%",""))/100)} -> 1400 | S98: Planned
A99: 8 | B99: Labourers | C99: Labour | D99: General Builder | L99: {=_xlfn.IFERROR(VLOOKUP(D99,'Lookups'!$A$2:$C$17,2,FALSE),0)} -> 45 | M99: 750 | P99: {=N99*O99} -> 0 | Q99: 0 | R99: {=(M99+P99)*(1+VALUE(SUBSTITUTE(Q99,"%",""))/100)} -> 750 | S99: Planned
A100: 8 | B100: Owen Brickwork | C100: Labour | D100: General Builder | G100: 1 day - to DPC | L100: {=_xlfn.IFERROR(VLOOKUP(D100,'Lookups'!$A$2:$C$17,2,FALSE),0)} -> 45 | M100: 275 | P100: {=N100*O100} -> 0 | Q100: 0 | R100: {=(M100+P100)*(1+VALUE(SUBSTITUTE(Q100,"%",""))/100)} -> 275 | S100: Planned
A101: 8 | L101: {=_xlfn.IFERROR(VLOOKUP(D101,'Lookups'!$A$2:$C$17,2,FALSE),0)} -> 0 | M101: {=K101*L101} -> 0 | P101: {=N101*O101} -> 0 | Q101: 20% | R101: {=(M101+P101)*(1+VALUE(SUBSTITUTE(Q101,"%",""))/100)} -> 0 | S101: Planned
...

Sheet Summary
A1: Project Summary
A2: Project Address: | B2: 46 Glenferrie Road, St Albans, AL1 4JU
A4: By Week (Totals)
A5: Week # | B5: Labour (£) | C5: Materials (£) | D5: Total incl. VAT (£) | E5: Completion % (manual)
A6: 1 | B6: {=SUMIF('Week-by-Week Plan'!$A$6:$A$293,A6,'Week-by-Week Plan'!$M$6:$M$293)} -> 1770 | C6: {=SUMIF('Week-by-Week Plan'!$A$6:$A$293,A6,'Week-by-Week Plan'!$P$6:$P$293)} -> 0 | D6: {=SUMIF('Week-by-Week Plan'!$A$6:$A$293,A6,'Week-by-Week Plan'!$R$6:$R$293)} -> 1770
A7: 2 | B7: {=SUMIF('Week-by-Week Plan'!$A$6:$A$293,A7,'Week-by-Week Plan'!$M$6:$M$293)} -> 1675 | C7: {=SUMIF('Week-by-Week Plan'!$A$6:$A$293,A7,'Week-by-Week Plan'!$P$6:$P$293)} -> 0 | D7: {=SUMIF('Week-by-Week Plan'!$A$6:$A$293,A7,'Week-by-Week Plan'!$R$6:$R$293)} -> 1675
A8: 3 | B8: {=SUMIF('Week-by-Week Plan'!$A$6:$A$293,A8,'Week-by-Week Plan'!$M$6:$M$293)} -> 525 | C8: {=SUMIF('Week-by-Week Plan'!$A$6:$A$293,A8,'Week-by-Week Plan'!$P$6:$P$293)} -> 0 | D8: {=SUMIF('Week-by-Week Plan'!$A$6:$A$293,A8,'Week-by-Week Plan'!$R$6:$R$293)} -> 525
A9: 4 | B9: {=SUMIF('Week-by-Week Plan'!$A$6:$A$293,A9,'Week-by-Week Plan'!$M$6:$M$293)} -> 1550 | C9: {=SUMIF('Week-by-Week Plan'!$A$6:$A$293,A9,'Week-by-Week Plan'!$P$6:$P$293)} -> 0 | D9: {=SUMIF('Week-by-Week Plan'!$A$6:$A$293,A9,'Week-by-Week Plan'!$R$6:$R$293)} -> 1550
A10: 5 | B10: {=SUMIF('Week-by-Week Plan'!$A$6:$A$293,A10,'Week-by-Week Plan'!$M$6:$M$293)} -> 3205 | C10: {=SUMIF('Week-by-Week Plan'!$A$6:$A$293,A10,'Week-by-Week Plan'!$P$6:$P$293)} -> 0 | D10: {=SUMIF('Week-by-Week Plan'!$A$6:$A$293,A10,'Week-by-Week Plan'!$R$6:$R$293)} -> 3205
A11: 6 | B11: {=SUMIF('Week-by-Week Plan'!$A$6:$A$293,A11,'Week-by-Week Plan'!$M$6:$M$293)} -> 2500 | C11: {=SUMIF('Week-by-Week Plan'!$A$6:$A$293,A11,'Week-by-Week Plan'!$P$6:$P$293)} -> 0 | D11: {=SUMIF('Week-by-Week Plan'!$A$6:$A$293,A11,'Week-by-Week Plan'!$R$6:$R$293)} -> 2500
A12: 7 | B12: {=SUMIF('Week-by-Week Plan'!$A$6:$A$293,A12,'Week-by-Week Plan'!$M$6:$M$293)} -> 1050 | C12: {=SUMIF('Week-by-Week Plan'!$A$6:$A$293,A12,'Week-by-Week Plan'!$P$6:$P$293)} -> 0 | D12: {=SUMIF('Week-by-Week Plan'!$A$6:$A$293,A12,'Week-by-Week Plan'!$R$6:$R$293)} -> 2048.4
A13: 8 | B13: {=SUMIF('Week-by-Week Plan'!$A$6:$A$293,A13,'Week-by-Week Plan'!$M$6:$M$293)} -> 2425 | C13: {=SUMIF('Week-by-Week Plan'!$A$6:$A$293,A13,'Week-by-Week Plan'!$P$6:$P$293)} -> 0 | D13: {=SUMIF('Week-by-Week Plan'!$A$6:$A$293,A13,'Week-by-Week Plan'!$R$6:$R$293)} -> 2425
A14: 9 | B14: {=SUMIF('Week-by-Week Plan'!$A$6:$A$293,A14,'Week-by-Week Plan'!$M$6:$M$293)} -> 6110 | C14: {=SUMIF('Week-by-Week Plan'!$A$6:$A$293,A14,'Week-by-Week Plan'!$P$6:$P$293)} -> 0 | D14: 6110
A15: 10 | B15: {=SUMIF('Week-by-Week Plan'!$A$6:$A$293,A15,'Week-by-Week Plan'!$M$6:$M$293)} -> 2915 | C15: {=SUMIF('Week-by-Week Plan'!$A$6:$A$293,A15,'Week-by-Week Plan'!$P$6:$P$293)} -> 0 | D15: 2915
A16: 11 | B16: {=SUMIF('Week-by-Week Plan'!$A$6:$A$293,A16,'Week-by-Week Plan'!$M$6:$M$293)} -> 700 | C16: {=SUMIF('Week-by-Week Plan'!$A$6:$A$293,A16,'Week-by-Week Plan'!$P$6:$P$293)} -> 0 | D16: 700
A17: 12 | B17: {=SUMIF('Week-by-Week Plan'!$A$6:$A$293,A17,'Week-by-Week Plan'!$M$6:$M$293)} -> 4000 | C17: {=SUMIF('Week-by-Week Plan'!$A$6:$A$293,A17,'Week-by-Week Plan'!$P$6:$P$293)} -> 0 | D17: 4000
A18: 13 | B18: {=SUMIF('Week-by-Week Plan'!$A$6:$A$293,A18,'Week-by-Week Plan'!$M$6:$M$293)} -> 2575 | C18: {=SUMIF('Week-by-Week Plan'!$A$6:$A$293,A18,'Week-by-Week Plan'!$P$6:$P$293)} -> 0 | D18: 2575
A19: 14 | B19: {=SUMIF('Week-by-Week Plan'!$A$6:$A$293,A19,'Week-by-Week Plan'!$M$6:$M$293)} -> 2520 | C19: {=SUMIF('Week-by-Week Plan'!$A$6:$A$293,A19,'Week-by-Week Plan'!$P$6:$P$293)} -> 0 | D19: {=SUMIF('Week-by-Week Plan'!$A$6:$A$293,A19,'Week-by-Week Plan'!$R$6:$R$293)} -> 2520
A20: 15 | B20: {=SUMIF('Week-by-Week Plan'!$A$6:$A$293,A20,'Week-by-Week Plan'!$M$6:$M$293)} -> 6997.84 | C20: {=SUMIF('Week-by-Week Plan'!$A$6:$A$293,A20,'Week-by-Week Plan'!$P$6:$P$293)} -> 0 | D20: {=SUMIF('Week-by-Week Plan'!$A$6:$A$293,A20,'Week-by-Week Plan'!$R$6:$R$293)} -> 7893.408
A21: 16 | B21: {=SUMIF('Week-by-Week Plan'!$A$6:$A$293,A21,'Week-by-Week Plan'!$M$6:$M$293)} -> 0 | C21: {=SUMIF('Week-by-Week Plan'!$A$6:$A$293,A21,'Week-by-Week Plan'!$P$6:$P$293)} -> 0 | D21: {=SUMIF('Week-by-Week Plan'!$A$6:$A$293,A21,'Week-by-Week Plan'!$R$6:$R$293)} -> 0
A22: 17 | B22: {=SUMIF('Week-by-Week Plan'!$A$6:$A$293,A22,'Week-by-Week Plan'!$M$6:$M$293)} -> 0 | C22: {=SUMIF('Week-by-Week Plan'!$A$6:$A$293,A22,'Week-by-Week Plan'!$P$6:$P$293)} -> 0 | D22: {=SUMIF('Week-by-Week Plan'!$A$6:$A$293,A22,'Week-by-Week Plan'!$R$6:$R$293)} -> 0
A23: 18 | B23: {=SUMIF('Week-by-Week Plan'!$A$6:$A$293,A23,'Week-by-Week Plan'!$M$6:$M$293)} -> 0 | C23: {=SUMIF('Week-by-Week Plan'!$A$6:$A$293,A23,'Week-by-Week Plan'!$P$6:$P$293)} -> 0 | D23: {=SUMIF('Week-by-Week Plan'!$A$6:$A$293,A23,'Week-by-Week Plan'!$R$6:$R$293)} -> 0
A24: 19 | B24: {=SUMIF('Week-by-Week Plan'!$A$6:$A$293,A24,'Week-by-Week Plan'!$M$6:$M$293)} -> 0 | C24: {=SUMIF('Week-by-Week Plan'!$A$6:$A$293,A24,'Week-by-Week Plan'!$P$6:$P$293)} -> 0 | D24: {=SUMIF('Week-by-Week Plan'!$A$6:$A$293,A24,'Week-by-Week Plan'!$R$6:$R$293)} -> 0
A25: 20 | B25: {=SUMIF('Week-by-Week Plan'!$A$6:$A$293,A25,'Week-by-Week Plan'!$M$6:$M$293)} -> 0 | C25: {=SUMIF('Week-by-Week Plan'!$A$6:$A$293,A25,'Week-by-Week Plan'!$P$6:$P$293)} -> 0 | D25: {=SUMIF('Week-by-Week Plan'!$A$6:$A$293,A25,'Week-by-Week Plan'!$R$6:$R$293)} -> 0
A26: 21 | B26: {=SUMIF('Week-by-Week Plan'!$A$6:$A$293,A26,'Week-by-Week Plan'!$M$6:$M$293)} -> 0 | C26: {=SUMIF('Week-by-Week Plan'!$A$6:$A$293,A26,'Week-by-Week Plan'!$P$6:$P$293)} -> 0 | D26: {=SUMIF('Week-by-Week Plan'!$A$6:$A$293,A26,'Week-by-Week Plan'!$R$6:$R$293)} -> 0
A27: 22 | B27: {=SUMIF('Week-by-Week Plan'!$A$6:$A$293,A27,'Week-by-Week Plan'!$M$6:$M$293)} -> 0 | C27: {=SUMIF('Week-by-Week Plan'!$A$6:$A$293,A27,'Week-by-Week Plan'!$P$6:$P$293)} -> 0 | D27: {=SUMIF('Week-by-Week Plan'!$A$6:$A$293,A27,'Week-by-Week Plan'!$R$6:$R$293)} -> 0
A29: Controls
A30: Target Budget (incl. VAT) | B30: 0
A31: Forecast Total (incl. VAT) | B31: {=SUM(D6:D27)} -> 42411.808
A32: Variance (Forecast - Budget) | B32: {=B31-B30} -> 42411.808
A33: Contingency % | B33: 0
A34: Contingency Amount | B34: {=B31*B33/100} -> 0
A35: Forecast + Contingency | B35: {=B31+B34} -> 42411.808
A38: How to use:
A39: 1) In 'Week-by-Week Plan', update each task with accurate hours/quantities and unit costs. 2) Choose Category, Trade, VAT and Status from dropdowns. 3) 'Summary' auto-aggregates totals by week and overall forecast. Tip: Duplicate/insert new rows as needed; keep formulas consistent.

Sheet Lookups
A1: Trade | B1: Default Labour Rate (£/hr) | C1: Default Markup %
A2: General Builder | B2: 45 | C2: 10
A3: Carpenter/Joiner | B3: 50 | C3: 10
A4: Plumber | B4: 60 | C4: 10
A5: Electrician | B5: 65 | C5: 10
A6: Plasterer | B6: 55 | C6: 10
A7: Tiler | B7: 55 | C7: 10
A8: Decorator | B8: 45 | C8: 10
A9: Roofer | B9: 60 | C9: 10
A10: Groundworker | B10: 55 | C10: 10
A11: Kitchen Fitter | B11: 55 | C11: 10
A12: Bathroom Fitter | B12: 55 | C12: 10
A13: Glazier | B13: 55 | C13: 10
... A17: Other | B17: 50 | C17: 10
